captchabuster/__init__.py
captchabuster/iconset/a/1425060488_3.gif
captchabuster/iconset/a/1425060648_1.gif
captchabuster/iconset/a/1425061720_3.gif
captchabuster/iconset/a/1425061725_3.gif
captchabuster/iconset/a/1425061851_1.gif
captchabuster/iconset/a/1425061857_1.gif
captchabuster/iconset/a/1425061874_5.gif
captchabuster/iconset/a/1425062064_2.gif
captchabuster/iconset/a/1425062087_4.gif
captchabuster/iconset/a/1425062139_1.gif
captchabuster/iconset/a/1425062218_1.gif
captchabuster/iconset/a/1425062271_4.gif
captchabuster/iconset/a/1425068216_2.gif
captchabuster/iconset/a/1425068426_1.gif
captchabuster/iconset/a/1425068426_5.gif
captchabuster/iconset/a/1425068525_1.gif
captchabuster/iconset/a/1425068593_0.gif
captchabuster/iconset/a/1425068593_4.gif
captchabuster/iconset/a/1425068670_4.gif
captchabuster/iconset/a/1425068692_1.gif
captchabuster/iconset/a/1425068952_3.gif
captchabuster/iconset/a/1425069055_0.gif
captchabuster/iconset/a/1425069078_2.gif
captchabuster/iconset/a/1425069143_1.gif
captchabuster/iconset/a/1425069229_1.gif
captchabuster/iconset/a/1425069229_5.gif
captchabuster/iconset/a/1425069285_0.gif
captchabuster/iconset/b/1425059900_3.gif
captchabuster/iconset/b/1425060783_0.gif
captchabuster/iconset/b/1425060865_4.gif
captchabuster/iconset/b/1425061225_2.gif
captchabuster/iconset/b/1425061225_3.gif
captchabuster/iconset/b/1425061233_2.gif
captchabuster/iconset/b/1425061233_4.gif
captchabuster/iconset/b/1425061747_3.gif
captchabuster/iconset/b/1425061821_4.gif
captchabuster/iconset/b/1425062116_1.gif
captchabuster/iconset/b/1425062139_3.gif
captchabuster/iconset/b/1425062328_1.gif
captchabuster/iconset/b/1425062354_5.gif
captchabuster/iconset/b/1425062383_5.gif
captchabuster/iconset/b/1425062409_1.gif
captchabuster/iconset/b/1425068272_3.gif
captchabuster/iconset/b/1425068299_0.gif
captchabuster/iconset/b/1425068325_0.gif
captchabuster/iconset/b/1425068345_5.gif
scrapy_amazon_robot_middleware3-0.2.3.dist-info/DESCRIPTION.rst
scrapy_amazon_robot_middleware3-0.2.3.dist-info/METADATA
scrapy_amazon_robot_middleware3-0.2.3.dist-info/RECORD
scrapy_amazon_robot_middleware3-0.2.3.dist-info/WHEEL
scrapy_amazon_robot_middleware3-0.2.3.dist-info/metadata.json
scrapy_amazon_robot_middleware3-0.2.3.dist-info/top_level.txt
