Metadata-Version: 2.0
Name: scrapy-amazon-robot-middleware3
Version: 0.2.3
Summary: Scrapy middleware module which uses image parsing to submit a captcha response to amazon.
Home-page: https://github.com/leon-wu/scrapy-amazon-robot-middleware
Author: Mark Sanders
Author-email: xmwlzhi@gmail.com
License: LICENSE.txt
Platform: UNKNOWN
Requires-Dist: beautifulsoup4 (==4.5.3)
Requires-Dist: pillow (==4.0.0)
Requires-Dist: requests (==2.13.0)
Requires-Dist: scrapy (==1.3.3)
